{
	"configurations" : 
	[
		{
			"directories" : 
			[
				{
					"build" : ".",
					"jsonFile" : "directory-.-Debug-f5ebdc15457944623624.json",
					"minimumCMakeVersion" : 
					{
						"string" : "3.16"
					},
					"projectIndex" : 0,
					"source" : ".",
					"targetIndexes" : 
					[
						0,
						1,
						2
					]
				}
			],
			"name" : "Debug",
			"projects" : 
			[
				{
					"directoryIndexes" : 
					[
						0
					],
					"name" : "kantenAnzeigen",
					"targetIndexes" : 
					[
						0,
						1,
						2
					]
				}
			],
			"targets" : 
			[
				{
					"directoryIndex" : 0,
					"id" : "kantenAnzeigen::@6890427a1f51a3e7e1df",
					"jsonFile" : "target-kantenAnzeigen-Debug-585ff0b4a53ea7df1937.json",
					"name" : "kantenAnzeigen",
					"projectIndex" : 0
				},
				{
					"directoryIndex" : 0,
					"id" : "kantenAnzeigen_autogen::@6890427a1f51a3e7e1df",
					"jsonFile" : "target-kantenAnzeigen_autogen-Debug-24849b81e1b24550a20b.json",
					"name" : "kantenAnzeigen_autogen",
					"projectIndex" : 0
				},
				{
					"directoryIndex" : 0,
					"id" : "kantenAnzeigen_autogen_timestamp_deps::@6890427a1f51a3e7e1df",
					"jsonFile" : "target-kantenAnzeigen_autogen_timestamp_deps-Debug-7e3affbbce5f7edd9748.json",
					"name" : "kantenAnzeigen_autogen_timestamp_deps",
					"projectIndex" : 0
				}
			]
		}
	],
	"kind" : "codemodel",
	"paths" : 
	{
		"build" : "/home/kimi-sickinger/Programmieren/qt/piecePilot_v2/build",
		"source" : "/home/kimi-sickinger/Programmieren/qt/piecePilot_v2"
	},
	"version" : 
	{
		"major" : 2,
		"minor" : 6
	}
}
